contentmap/__init__.py
contentmap/core.py
contentmap/sitemap.py
contentmap/vss.py
contentmap-0.5.0.dist-info/METADATA
contentmap-0.5.0.dist-info/WHEEL
contentmap-0.5.0.dist-info/RECORD
