Metadata-Version: 2.1
Name: contentmap
Version: 0.5.0
Summary: 
Author: Philippe Oger
Author-email: phil.oger@gmail.com
Requires-Python: >=3.9,<4.0
Classifier: Programming Language :: Python :: 3
Classifier: Programming Language :: Python :: 3.9
Classifier: Programming Language :: Python :: 3.10
Classifier: Programming Language :: Python :: 3.11
Classifier: Programming Language :: Python :: 3.12
Requires-Dist: aiohttp (>=3.9.1,<4.0.0)
Requires-Dist: langchain (>=0.1.8,<0.2.0)
Requires-Dist: lxml (==4.9.4)
Requires-Dist: requests (>=2.31.0,<3.0.0)
Requires-Dist: sentence-transformers (>=2.3.1,<3.0.0)
Requires-Dist: sqlite-vss (>=0.1.2,<0.2.0)
Requires-Dist: tqdm (>=4.66.1,<5.0.0)
Requires-Dist: trafilatura (>=1.6.4,<2.0.0)
